wkafka/__init__.py
wkafka/controller/__init__.py
wkafka/controller/wkafka.py
wkafka-0.2.1.dist-info/LICENSE
wkafka-0.2.1.dist-info/METADATA
wkafka-0.2.1.dist-info/WHEEL
wkafka-0.2.1.dist-info/top_level.txt
wkafka-0.2.1.dist-info/RECORD
