Metadata-Version: 2.2
Name: wkafka
Version: 0.2.1
Summary: Pipeline con API para gestión de productores y consumidores de Kafka.
Home-page: https://github.com/wisrovi/wkafka/issues
Author: wisrovi
Author-email: wisrovi <wisrovi.rodriguez@gmail.com>
License: MIT License
Project-URL: Homepage, https://github.com/wisrovi/wkafka
Project-URL: Bug Tracker, https://github.com/wisrovi/wkafka/issues
Classifier: Programming Language :: Python :: 3
Classifier: License :: OSI Approved :: MIT License
Classifier: Operating System :: OS Independent
Requires-Python: >=3.6, <3.11
License-File: LICENSE
Requires-Dist: loguru
Requires-Dist: toml
Requires-Dist: setuptools
Requires-Dist: opencv-python
Requires-Dist: kafka-python
Requires-Dist: rich
Requires-Dist: requests
Requires-Dist: numpy
Requires-Dist: pillow
Requires-Dist: python-snappy
Dynamic: author
Dynamic: home-page
Dynamic: requires-python
